manim_present/CustomMobjects.py
manim_present/__init__.py
manim_present/manim_present.py
manim_present/manim_present_cli.py
manim_present-0.1.0.dist-info/METADATA
manim_present-0.1.0.dist-info/WHEEL
manim_present-0.1.0.dist-info/entry_points.txt
manim_present-0.1.0.dist-info/licenses/LICENSE
manim_present-0.1.0.dist-info/RECORD
