Metadata-Version: 2.3
Name: manim-present
Version: 0.1.0
Summary: Configuration-based HTML presentation producer using Manim.
Project-URL: Homepage, https://github.com/FoamScience/manim-present
Project-URL: Bug Tracker, https://github.com/FoamScience/manim-present/issues
Author-email: Mohammed Elwardi Fadeli <elwardifadeli@gmail.com>
Classifier: Development Status :: 2 - Pre-Alpha
Classifier: Intended Audience :: Education
Classifier: Intended Audience :: Science/Research
Classifier: License :: OSI Approved :: MIT License
Classifier: Operating System :: OS Independent
Classifier: Programming Language :: Python :: 3
Classifier: Topic :: Multimedia :: Graphics :: Presentation
Requires-Python: >=3.10
Requires-Dist: ffmpeg-python>=0.2.0
Requires-Dist: hydra-core>=1.3.2
Requires-Dist: manim-slides>=5.1.10
Requires-Dist: manim>=0.18.1
Requires-Dist: numpy>=1.26.4
Requires-Dist: omegaconf>=2.3.0
Requires-Dist: opencv-python>=4.10.0.84
Requires-Dist: pandas>=2.2.3
Requires-Dist: pybtex>=0.24.0
Requires-Dist: pypdf2>=3.0.1
Requires-Dist: scipy>=1.14.1
